s2terminal_lex_rank_summarizer/__init__.py
s2terminal_lex_rank_summarizer/main.py
s2terminal_lex_rank_summarizer/summarize.py
s2terminal_lex_rank_summarizer-0.1.2.dist-info/entry_points.txt
s2terminal_lex_rank_summarizer-0.1.2.dist-info/LICENSE
s2terminal_lex_rank_summarizer-0.1.2.dist-info/WHEEL
s2terminal_lex_rank_summarizer-0.1.2.dist-info/METADATA
s2terminal_lex_rank_summarizer-0.1.2.dist-info/RECORD
