Metadata-Version: 2.1
Name: s2terminal-lex-rank-summarizer
Version: 0.1.2
Summary: This is a CLI tool that uses LexRank to translate sentences in 3 lines.
Home-page: https://github.com/s2terminal/lex-rank-summarizer
License: MIT
Author: s2terminal
Author-email: suzuki.sh@s2terminal.com
Requires-Python: >=3.9,<4.0
Classifier: License :: OSI Approved :: MIT License
Classifier: Programming Language :: Python :: 3
Classifier: Programming Language :: Python :: 3.9
Requires-Dist: Janome (>=0.4.1,<0.5.0)
Requires-Dist: fire (>=0.4.0,<0.5.0)
Requires-Dist: numpy (>=1.21.0,<2.0.0)
Requires-Dist: sumy (>=0.8.1,<0.9.0)
Requires-Dist: tinysegmenter (>=0.4,<0.5)
Project-URL: Repository, https://github.com/s2terminal/lex-rank-summarizer
